pycan/__init__.py
pycan/clinical/__init__.py
pycan/data/__init__.py
pycan/data/loaders.py
pycan/evaluation/__init__.py
pycan/evaluation/metrics.py
pycan/features/__init__.py
pycan/genomics/__init__.py
pycan/imaging/__init__.py
pycan/models/__init__.py
pycan/models/classifiers.py
pycan/utils/__init__.py
pycan_research-1.0.0.dist-info/METADATA
pycan_research-1.0.0.dist-info/WHEEL
pycan_research-1.0.0.dist-info/top_level.txt
pycan_research-1.0.0.dist-info/RECORD
