Metadata-Version: 2.4
Name: pycan-research
Version: 1.0.0
Summary: Comprehensive Python library for cancer research
Author: Balaga Raghuram
Requires-Python: >=3.8
Requires-Dist: numpy>=1.20.0
Requires-Dist: scikit-learn>=1.0.0
Dynamic: author
Dynamic: description
Dynamic: requires-dist
Dynamic: requires-python
Dynamic: summary
